milliedashmaker/__init__.py
milliedashmaker/ag-grid-cookiecutter/cookiecutter.json
milliedashmaker/ag-grid-cookiecutter/{{cookiecutter.folder_name}}/app.py
milliedashmaker/dash-knob-cookiecutter/cookiecutter.json
milliedashmaker/dash-knob-cookiecutter/{{cookiecutter.folder_name}}/app.py
milliedashmaker/dash-table-cookiecutter/cookiecutter.json
milliedashmaker/dash-table-cookiecutter/{{cookiecutter.folder_name}}/app.py
milliedashmaker/main.py
milliedashmaker-0.1.1.dist-info/METADATA
milliedashmaker-0.1.1.dist-info/WHEEL
milliedashmaker-0.1.1.dist-info/RECORD
